llmlib/__init__.py
llmlib/core.py
llmlib/images.py
llmlib/py.typed
llmlib_amq-0.0.9.dist-info/LICENSE
llmlib_amq-0.0.9.dist-info/WHEEL
llmlib_amq-0.0.9.dist-info/METADATA
llmlib_amq-0.0.9.dist-info/RECORD
