Metadata-Version: 2.1
Name: llmlib-amq
Version: 0.0.9
Summary: A simple library for making requests to LLMs
Author-email: Armand McQueen <armandmcqueen@gmail.com>
Requires-Python: >=3.10
Classifier: Programming Language :: Python :: 3
Classifier: License :: OSI Approved :: MIT License
Classifier: Operating System :: OS Independent
Requires-Dist: pydantic
Requires-Dist: openai
Requires-Dist: anthropic
Requires-Dist: rich
Requires-Dist: Pillow>=10.4.0
Project-URL: Documentation, https://github.com/armandmcqueen/llmlib#readme
Project-URL: Home, https://github.com/armandmcqueen/llmlib
Project-URL: Issues, https://github.com/armandmcqueen/llmlib/issues
